MANIFEST.in
setup.cfg
setup.py
django_mgof.egg-info/PKG-INFO
django_mgof.egg-info/SOURCES.txt
django_mgof.egg-info/dependency_links.txt
django_mgof.egg-info/not-zip-safe
django_mgof.egg-info/requires.txt
django_mgof.egg-info/top_level.txt
mgof/__init__.py
mgof/admin.py
mgof/apps.py
mgof/conf.py
mgof/forms.py
mgof/models.py
mgof/signals.py
mgof/urls.py
mgof/utils.py
mgof/views.py
mgof/locale/fr/LC_MESSAGES/django.mo
mgof/locale/fr/LC_MESSAGES/django.po
mgof/migrations/0001_initial.py
mgof/migrations/__init__.py
mgof/migrations/__init__.pyc
mgof/static/mgof/css/mgof.css
mgof/static/mgof/js/utils.js
mgof/templates/mgof/forum_detail.html
mgof/templates/mgof/index.html
mgof/templates/mgof/messages_display.html
mgof/templates/mgof/moderation_queue.html
mgof/templates/mgof/topic_detail.html
mgof/templates/mgof/forum/paginate.html
mgof/templates/mgof/forum/print_forum.html
mgof/templates/mgof/post/create.html
mgof/templates/mgof/post/moderate_actionbar.html
mgof/templates/mgof/post/moderate_success_actionbar.html
mgof/templates/mgof/post/moderation_confirm.html
mgof/templates/mgof/tags/forums_recent_entries.html
mgof/templates/mgof/topic/create.html
mgof/templates/mgof/topic/paginate.html
mgof/templates/mgof/topic/set_monitoring.html
mgof/templates/mgof/topic/switch_open.html
mgof/templatetags/__init__.py
mgof/templatetags/__init__.pyc
mgof/templatetags/mgof.py
mgof/templatetags/mgof.pyc
mgof/tests/__init__.py
mgof/tests/__init__.pyc
mgof/tests/factory.py
mgof/tests/test_models.py
mgof/tests/test_models.pyc
mgof/tests/test_views.py
mgof/tests/__pycache__/test_models.cpython-27-PYTEST.pyc